{
    "swagger": "2.0",
    "info": {
        "description": "RESTful API for the TodoList microservice.",
        "title": "Service for compiling task lists",
        "contact": {},
        "version": "1.0"
    },
    "host": "localhost:8080",
    "basePath": "/api/todo-list",
    "paths": {
        "/tasks": {
            "get": {
                "produces": [
                    "application/json"
                ],
                "tags": [
                    "todo"
                ],
                "summary": "get todo",
                "parameters": [
                    {
                        "type": "string",
                        "default": "active",
                        "description": "Status of the todo",
                        "name": "status",
                        "in": "query"
                    }
                ],
                "responses": {
                    "200": {
                        "description": "OK",
                        "schema": {
                            "type": "array",
                            "items": {
                                "$ref": "#/definitions/domain.TodoModel"
                            }
                        }
                    },
                    "400": {
                        "description": "Bad Request",
                        "schema": {
                            "$ref": "#/definitions/response.Object"
                        }
                    },
                    "404": {
                        "description": "Not Found",
                        "schema": {
                            "$ref": "#/definitions/response.Object"
                        }
                    },
                    "500": {
                        "description": "Internal Server Error",
                        "schema": {
                            "$ref": "#/definitions/response.Object"
                        }
                    }
                }
            },
            "post": {
                "consumes": [
                    "application/json"
                ],
                "produces": [
                    "application/json"
                ],
                "tags": [
                    "todo"
                ],
                "summary": "add newTodo",
                "parameters": [
                    {
                        "description": "todoModel request",
                        "name": "input",
                        "in": "body",
                        "required": true,
                        "schema": {
                            "$ref": "#/definitions/domain.TodoModel"
                        }
                    }
                ],
                "responses": {
                    "200": {
                        "description": "OK",
                        "schema": {
                            "$ref": "#/definitions/domain.TodoModel"
                        }
                    },
                    "400": {
                        "description": "Bad Request",
                        "schema": {
                            "$ref": "#/definitions/response.Object"
                        }
                    },
                    "404": {
                        "description": "Not Found",
                        "schema": {
                            "$ref": "#/definitions/response.Object"
                        }
                    },
                    "500": {
                        "description": "Internal Server Error",
                        "schema": {
                            "$ref": "#/definitions/response.Object"
                        }
                    }
                }
            }
        },
        "/tasks/{id}": {
            "put": {
                "consumes": [
                    "application/json"
                ],
                "produces": [
                    "application/json"
                ],
                "tags": [
                    "todo"
                ],
                "summary": "update todo by id",
                "parameters": [
                    {
                        "type": "string",
                        "description": "todo id",
                        "name": "id",
                        "in": "path",
                        "required": true
                    },
                    {
                        "description": "todoModel request",
                        "name": "input",
                        "in": "body",
                        "required": true,
                        "schema": {
                            "$ref": "#/definitions/domain.TodoModel"
                        }
                    }
                ],
                "responses": {
                    "204": {
                        "description": "No Content"
                    },
                    "400": {
                        "description": "Bad Request",
                        "schema": {
                            "$ref": "#/definitions/response.Object"
                        }
                    },
                    "404": {
                        "description": "Not Found",
                        "schema": {
                            "$ref": "#/definitions/response.Object"
                        }
                    },
                    "500": {
                        "description": "Internal Server Error",
                        "schema": {
                            "$ref": "#/definitions/response.Object"
                        }
                    }
                }
            },
            "delete": {
                "tags": [
                    "todo"
                ],
                "summary": "delete todo by id",
                "parameters": [
                    {
                        "type": "string",
                        "description": "todo id",
                        "name": "id",
                        "in": "path",
                        "required": true
                    }
                ],
                "responses": {
                    "204": {
                        "description": "No Content"
                    },
                    "400": {
                        "description": "Bad Request",
                        "schema": {
                            "$ref": "#/definitions/response.Object"
                        }
                    },
                    "404": {
                        "description": "Not Found",
                        "schema": {
                            "$ref": "#/definitions/response.Object"
                        }
                    },
                    "500": {
                        "description": "Internal Server Error",
                        "schema": {
                            "$ref": "#/definitions/response.Object"
                        }
                    }
                }
            }
        },
        "/tasks/{id}/done": {
            "put": {
                "tags": [
                    "todo"
                ],
                "summary": "mark todo by id",
                "parameters": [
                    {
                        "type": "string",
                        "description": "todo id",
                        "name": "id",
                        "in": "path",
                        "required": true
                    },
                    {
                        "description": "Todo Status",
                        "name": "input",
                        "in": "body",
                        "required": true,
                        "schema": {
                            "$ref": "#/definitions/domain.TodoModel"
                        }
                    }
                ],
                "responses": {
                    "204": {
                        "description": "No Content"
                    },
                    "400": {
                        "description": "Bad Request",
                        "schema": {
                            "$ref": "#/definitions/response.Object"
                        }
                    },
                    "404": {
                        "description": "Not Found",
                        "schema": {
                            "$ref": "#/definitions/response.Object"
                        }
                    },
                    "500": {
                        "description": "Internal Server Error",
                        "schema": {
                            "$ref": "#/definitions/response.Object"
                        }
                    }
                }
            }
        }
    },
    "definitions": {
        "domain.TodoModel": {
            "type": "object",
            "properties": {
                "activeAt": {
                    "type": "string"
                },
                "id": {
                    "type": "string"
                },
                "status": {
                    "type": "string"
                },
                "title": {
                    "type": "string"
                }
            }
        },
        "response.Object": {
            "type": "object",
            "properties": {
                "data": {},
                "message": {
                    "type": "string"
                },
                "success": {
                    "type": "boolean"
                }
            }
        }
    }
}